setuptools_setup_versions/__init__.py
setuptools_setup_versions/find.py
setuptools_setup_versions/parse.py
setuptools_setup_versions/requirements.py
setuptools_setup_versions-1.18.0.dist-info/METADATA
setuptools_setup_versions-1.18.0.dist-info/WHEEL
setuptools_setup_versions-1.18.0.dist-info/top_level.txt
setuptools_setup_versions-1.18.0.dist-info/RECORD
