Metadata-Version: 2.1
Name: setuptools-setup-versions
Version: 1.18.0
Summary: Automatically update setup.py `install_requires`, `extras_require`,and/or `setup_requires` version numbers for PIP packages
Home-page: UNKNOWN
Author: David Belais
Author-email: david@belais.me
License: UNKNOWN
Keywords: setuptools install_requires version
Platform: UNKNOWN
Requires-Python: ~=3.6
Requires-Dist: setuptools (>=57.4)
Requires-Dist: pip (>=21.2)
Requires-Dist: more-itertools (>=8.8)
Requires-Dist: packaging (>=21.0)
Requires-Dist: dataclasses
Provides-Extra: all
Requires-Dist: tox (~=3.20) ; extra == 'all'
Requires-Dist: pytest (~=6.2) ; extra == 'all'
Requires-Dist: twine (~=3.3) ; extra == 'all'
Requires-Dist: pytest (>=6.2) ; extra == 'all'
Requires-Dist: wheel (~=0.36) ; extra == 'all'
Requires-Dist: readme-md-docstrings (<1,>=0.1.0) ; extra == 'all'
Requires-Dist: daves-dev-tools (~=0.3) ; extra == 'all'
Provides-Extra: dev
Requires-Dist: twine (~=3.3) ; extra == 'dev'
Requires-Dist: tox (~=3.20) ; extra == 'dev'
Requires-Dist: pytest (>=6.2) ; extra == 'dev'
Requires-Dist: wheel (~=0.36) ; extra == 'dev'
Requires-Dist: readme-md-docstrings (<1,>=0.1.0) ; extra == 'dev'
Requires-Dist: daves-dev-tools (~=0.3) ; extra == 'dev'
Provides-Extra: test
Requires-Dist: tox (~=3.20) ; extra == 'test'
Requires-Dist: pytest (~=6.2) ; extra == 'test'
